ai_test_designer/__init__.py
ai_test_designer/ai_test_designer.py
ai_test_designer/ai_test_designer_library.py
cqe_aitestbot-0.0.8.dist-info/LICENSE
cqe_aitestbot-0.0.8.dist-info/METADATA
cqe_aitestbot-0.0.8.dist-info/WHEEL
cqe_aitestbot-0.0.8.dist-info/entry_points.txt
cqe_aitestbot-0.0.8.dist-info/top_level.txt
cqe_aitestbot-0.0.8.dist-info/RECORD
